oora/__init__.py
oora/py.typed
oora-0.2.6.dist-info/METADATA
oora-0.2.6.dist-info/WHEEL
oora-0.2.6.dist-info/RECORD
