Metadata-Version: 2.4
Name: oora
Version: 0.2.6
Summary: Thin layer above sqlite3
Author-email: Mickaël Desfrênes <mickael.desfrenes@unicaen.fr>
License: CECILL-C
Requires-Python: >=3.9
